LICENSE.txt
README.rst
pyproject.toml
requirements.txt
igbpyutils/__init__.py
igbpyutils/dt.py
igbpyutils/error.py
igbpyutils/file.py
igbpyutils/iter.py
igbpyutils/test.py
igbpyutils.egg-info/PKG-INFO
igbpyutils.egg-info/SOURCES.txt
igbpyutils.egg-info/dependency_links.txt
igbpyutils.egg-info/entry_points.txt
igbpyutils.egg-info/requires.txt
igbpyutils.egg-info/top_level.txt
igbpyutils/dev/__init__.py
igbpyutils/dev/script_vs_lib/__init__.py
igbpyutils/dev/script_vs_lib/__main__.py
tests/test_dir_iteration.py
tests/test_dt.py
tests/test_error.py
tests/test_file.py
tests/test_iter.py
tests/test_iter_patterns.py
tests/test_script_vs_lib.py
tests/test_test.py